divami_lib/__init__.py
divami_lib/x.py
divami_lib/y.py
divami_lib/z/__init__.py
divami_lib/z/z1.py
divami_lib-0.1.1.dist-info/METADATA
divami_lib-0.1.1.dist-info/WHEEL
divami_lib-0.1.1.dist-info/entry_points.txt
divami_lib-0.1.1.dist-info/top_level.txt
divami_lib-0.1.1.dist-info/RECORD
