Metadata-Version: 2.4
Name: divami_lib
Version: 0.1.1
Summary: A command-line todo tracker application
Author: Yeshwanth
Classifier: Programming Language :: Python :: 3
Classifier: Operating System :: OS Independent
Requires-Python: >=3.8
Dynamic: author
Dynamic: classifier
Dynamic: requires-python
Dynamic: summary
